[
  {
    "id": "counter-1761435507469",
    "name": "Param",
    "value": 0,
    "lastUpdated": 1761435507470,
    "dailyGoal": 10,
    "users": {
      "Param": 0
    },
    "history": {
      "2025-10-25": {
        "users": {
          "Param": 0
        },
        "total": 0,
        "day": "Saturday"
      }
    }
  },
  {
    "id": "counter-1761435517755",
    "name": "Prabh",
    "value": 10,
    "lastUpdated": 1761435582067,
    "dailyGoal": 10,
    "users": {
      "Prabh": 4,
      "Simran": 4,
      "Param": 2
    },
    "history": {
      "2025-10-25": {
        "users": {
          "Prabh": 4,
          "Simran": 4,
          "Param": 2
        },
        "total": 10,
        "day": "Saturday"
      }
    },
    "dailyCount": 10
  }
]